<annotation>
	<folder>切图</folder>
	<filename>001652.jpg</filename>
	<path>/home/fukai/图片/切图/001652.jpg</path>
	<source>
		<database>Unknown</database>
	</source>
	<size>
		<width>468</width>
		<height>468</height>
		<depth>3</depth>
	</size>
	<segmented>0</segmented>
	<object>
		<name>breakpoint</name>
		<pose>Unspecified</pose>
		<truncated>0</truncated>
		<difficult>0</difficult>
		<bndbox>
			<xmin>156</xmin>
			<ymin>124</ymin>
			<xmax>217</xmax>
			<ymax>170</ymax>
		</bndbox>
	</object>
	<object>
		<name>breakpoint</name>
		<pose>Unspecified</pose>
		<truncated>0</truncated>
		<difficult>0</difficult>
		<bndbox>
			<xmin>158</xmin>
			<ymin>237</ymin>
			<xmax>219</xmax>
			<ymax>283</ymax>
		</bndbox>
	</object>
	<object>
		<name>breakpoint</name>
		<pose>Unspecified</pose>
		<truncated>0</truncated>
		<difficult>0</difficult>
		<bndbox>
			<xmin>161</xmin>
			<ymin>181</ymin>
			<xmax>222</xmax>
			<ymax>227</ymax>
		</bndbox>
	</object>
</annotation>
