<annotation>
	<folder>pic</folder>
	<filename>103.jpg</filename>
	<path>/home/glovaer/labelImg/pic/103.jpg</path>
	<source>
		<database>Unknown</database>
	</source>
	<size>
		<width>512</width>
		<height>512</height>
		<depth>1</depth>
	</size>
	<segmented>0</segmented>
	<object>
		<name>defect</name>
		<pose>Unspecified</pose>
		<truncated>0</truncated>
		<difficult>0</difficult>
		<bndbox>
			<xmin>129</xmin>
			<ymin>310</ymin>
			<xmax>168</xmax>
			<ymax>353</ymax>
		</bndbox>
	</object>
	<object>
		<name>defect</name>
		<pose>Unspecified</pose>
		<truncated>0</truncated>
		<difficult>0</difficult>
		<bndbox>
			<xmin>351</xmin>
			<ymin>204</ymin>
			<xmax>390</xmax>
			<ymax>246</ymax>
		</bndbox>
	</object>
</annotation>
