<annotation>
	<folder>pic</folder>
	<filename>429.jpg</filename>
	<path>/home/glovaer/labelImg/pic/429.jpg</path>
	<source>
		<database>Unknown</database>
	</source>
	<size>
		<width>512</width>
		<height>512</height>
		<depth>1</depth>
	</size>
	<segmented>0</segmented>
	<object>
		<name>defect</name>
		<pose>Unspecified</pose>
		<truncated>0</truncated>
		<difficult>0</difficult>
		<bndbox>
			<xmin>181</xmin>
			<ymin>284</ymin>
			<xmax>217</xmax>
			<ymax>318</ymax>
		</bndbox>
	</object>
	<object>
		<name>defect</name>
		<pose>Unspecified</pose>
		<truncated>0</truncated>
		<difficult>0</difficult>
		<bndbox>
			<xmin>294</xmin>
			<ymin>353</ymin>
			<xmax>334</xmax>
			<ymax>389</ymax>
		</bndbox>
	</object>
</annotation>
