<annotation>
	<folder>pic</folder>
	<filename>523.jpg</filename>
	<path>/home/glovaer/labelImg/pic/523.jpg</path>
	<source>
		<database>Unknown</database>
	</source>
	<size>
		<width>512</width>
		<height>512</height>
		<depth>1</depth>
	</size>
	<segmented>0</segmented>
	<object>
		<name>defect</name>
		<pose>Unspecified</pose>
		<truncated>0</truncated>
		<difficult>0</difficult>
		<bndbox>
			<xmin>211</xmin>
			<ymin>26</ymin>
			<xmax>294</xmax>
			<ymax>69</ymax>
		</bndbox>
	</object>
	<object>
		<name>defect</name>
		<pose>Unspecified</pose>
		<truncated>0</truncated>
		<difficult>0</difficult>
		<bndbox>
			<xmin>277</xmin>
			<ymin>229</ymin>
			<xmax>361</xmax>
			<ymax>271</ymax>
		</bndbox>
	</object>
	<object>
		<name>defect</name>
		<pose>Unspecified</pose>
		<truncated>0</truncated>
		<difficult>0</difficult>
		<bndbox>
			<xmin>168</xmin>
			<ymin>365</ymin>
			<xmax>252</xmax>
			<ymax>412</ymax>
		</bndbox>
	</object>
</annotation>
