<annotation>
	<folder>pic</folder>
	<filename>644.jpg</filename>
	<path>/home/glovaer/labelImg/pic/644.jpg</path>
	<source>
		<database>Unknown</database>
	</source>
	<size>
		<width>512</width>
		<height>512</height>
		<depth>1</depth>
	</size>
	<segmented>0</segmented>
	<object>
		<name>defect</name>
		<pose>Unspecified</pose>
		<truncated>0</truncated>
		<difficult>0</difficult>
		<bndbox>
			<xmin>246</xmin>
			<ymin>273</ymin>
			<xmax>315</xmax>
			<ymax>316</ymax>
		</bndbox>
	</object>
	<object>
		<name>defect</name>
		<pose>Unspecified</pose>
		<truncated>0</truncated>
		<difficult>0</difficult>
		<bndbox>
			<xmin>405</xmin>
			<ymin>114</ymin>
			<xmax>477</xmax>
			<ymax>156</ymax>
		</bndbox>
	</object>
	<object>
		<name>defect</name>
		<pose>Unspecified</pose>
		<truncated>0</truncated>
		<difficult>0</difficult>
		<bndbox>
			<xmin>361</xmin>
			<ymin>225</ymin>
			<xmax>433</xmax>
			<ymax>260</ymax>
		</bndbox>
	</object>
	<object>
		<name>defect</name>
		<pose>Unspecified</pose>
		<truncated>0</truncated>
		<difficult>0</difficult>
		<bndbox>
			<xmin>339</xmin>
			<ymin>279</ymin>
			<xmax>414</xmax>
			<ymax>321</ymax>
		</bndbox>
	</object>
</annotation>
