<annotation>
	<folder>pic</folder>
	<filename>783.jpg</filename>
	<path>/home/glovaer/labelImg/pic/783.jpg</path>
	<source>
		<database>Unknown</database>
	</source>
	<size>
		<width>512</width>
		<height>512</height>
		<depth>1</depth>
	</size>
	<segmented>0</segmented>
	<object>
		<name>defect</name>
		<pose>Unspecified</pose>
		<truncated>0</truncated>
		<difficult>0</difficult>
		<bndbox>
			<xmin>72</xmin>
			<ymin>73</ymin>
			<xmax>120</xmax>
			<ymax>127</ymax>
		</bndbox>
	</object>
	<object>
		<name>defect</name>
		<pose>Unspecified</pose>
		<truncated>0</truncated>
		<difficult>0</difficult>
		<bndbox>
			<xmin>261</xmin>
			<ymin>173</ymin>
			<xmax>307</xmax>
			<ymax>234</ymax>
		</bndbox>
	</object>
	<object>
		<name>defect</name>
		<pose>Unspecified</pose>
		<truncated>0</truncated>
		<difficult>0</difficult>
		<bndbox>
			<xmin>271</xmin>
			<ymin>353</ymin>
			<xmax>326</xmax>
			<ymax>407</ymax>
		</bndbox>
	</object>
</annotation>
