<annotation>
	<folder>pic</folder>
	<filename>1204.jpg</filename>
	<path>/home/glovaer/labelImg/pic/1204.jpg</path>
	<source>
		<database>Unknown</database>
	</source>
	<size>
		<width>512</width>
		<height>512</height>
		<depth>1</depth>
	</size>
	<segmented>0</segmented>
	<object>
		<name>defect</name>
		<pose>Unspecified</pose>
		<truncated>0</truncated>
		<difficult>0</difficult>
		<bndbox>
			<xmin>87</xmin>
			<ymin>16</ymin>
			<xmax>138</xmax>
			<ymax>62</ymax>
		</bndbox>
	</object>
	<object>
		<name>defect</name>
		<pose>Unspecified</pose>
		<truncated>0</truncated>
		<difficult>0</difficult>
		<bndbox>
			<xmin>217</xmin>
			<ymin>321</ymin>
			<xmax>274</xmax>
			<ymax>368</ymax>
		</bndbox>
	</object>
</annotation>
