<annotation>
	<folder>pic</folder>
	<filename>2119.jpg</filename>
	<path>/home/glovaer/labelImg/pic/2119.jpg</path>
	<source>
		<database>Unknown</database>
	</source>
	<size>
		<width>512</width>
		<height>512</height>
		<depth>1</depth>
	</size>
	<segmented>0</segmented>
	<object>
		<name>defect</name>
		<pose>Unspecified</pose>
		<truncated>0</truncated>
		<difficult>0</difficult>
		<bndbox>
			<xmin>90</xmin>
			<ymin>83</ymin>
			<xmax>128</xmax>
			<ymax>119</ymax>
		</bndbox>
	</object>
	<object>
		<name>defect</name>
		<pose>Unspecified</pose>
		<truncated>0</truncated>
		<difficult>0</difficult>
		<bndbox>
			<xmin>152</xmin>
			<ymin>376</ymin>
			<xmax>190</xmax>
			<ymax>414</ymax>
		</bndbox>
	</object>
</annotation>
