<annotation>
	<folder>pic</folder>
	<filename>2198.jpg</filename>
	<path>/home/glovaer/labelImg/pic/2198.jpg</path>
	<source>
		<database>Unknown</database>
	</source>
	<size>
		<width>512</width>
		<height>512</height>
		<depth>1</depth>
	</size>
	<segmented>0</segmented>
	<object>
		<name>defect</name>
		<pose>Unspecified</pose>
		<truncated>0</truncated>
		<difficult>0</difficult>
		<bndbox>
			<xmin>436</xmin>
			<ymin>90</ymin>
			<xmax>453</xmax>
			<ymax>105</ymax>
		</bndbox>
	</object>
	<object>
		<name>defect</name>
		<pose>Unspecified</pose>
		<truncated>0</truncated>
		<difficult>0</difficult>
		<bndbox>
			<xmin>437</xmin>
			<ymin>69</ymin>
			<xmax>452</xmax>
			<ymax>84</ymax>
		</bndbox>
	</object>
	<object>
		<name>defect</name>
		<pose>Unspecified</pose>
		<truncated>0</truncated>
		<difficult>0</difficult>
		<bndbox>
			<xmin>436</xmin>
			<ymin>48</ymin>
			<xmax>452</xmax>
			<ymax>62</ymax>
		</bndbox>
	</object>
	<object>
		<name>defect</name>
		<pose>Unspecified</pose>
		<truncated>0</truncated>
		<difficult>0</difficult>
		<bndbox>
			<xmin>376</xmin>
			<ymin>66</ymin>
			<xmax>392</xmax>
			<ymax>84</ymax>
		</bndbox>
	</object>
	<object>
		<name>defect</name>
		<pose>Unspecified</pose>
		<truncated>0</truncated>
		<difficult>0</difficult>
		<bndbox>
			<xmin>171</xmin>
			<ymin>334</ymin>
			<xmax>186</xmax>
			<ymax>348</ymax>
		</bndbox>
	</object>
	<object>
		<name>defect</name>
		<pose>Unspecified</pose>
		<truncated>0</truncated>
		<difficult>0</difficult>
		<bndbox>
			<xmin>406</xmin>
			<ymin>384</ymin>
			<xmax>422</xmax>
			<ymax>399</ymax>
		</bndbox>
	</object>
</annotation>
