<annotation>
	<folder>pic</folder>
	<filename>2320.jpg</filename>
	<path>/home/glovaer/labelImg/pic/2320.jpg</path>
	<source>
		<database>Unknown</database>
	</source>
	<size>
		<width>512</width>
		<height>512</height>
		<depth>1</depth>
	</size>
	<segmented>0</segmented>
	<object>
		<name>defect</name>
		<pose>Unspecified</pose>
		<truncated>0</truncated>
		<difficult>0</difficult>
		<bndbox>
			<xmin>74</xmin>
			<ymin>244</ymin>
			<xmax>93</xmax>
			<ymax>262</ymax>
		</bndbox>
	</object>
	<object>
		<name>defect</name>
		<pose>Unspecified</pose>
		<truncated>0</truncated>
		<difficult>0</difficult>
		<bndbox>
			<xmin>159</xmin>
			<ymin>224</ymin>
			<xmax>177</xmax>
			<ymax>241</ymax>
		</bndbox>
	</object>
	<object>
		<name>defect</name>
		<pose>Unspecified</pose>
		<truncated>0</truncated>
		<difficult>0</difficult>
		<bndbox>
			<xmin>436</xmin>
			<ymin>397</ymin>
			<xmax>454</xmax>
			<ymax>416</ymax>
		</bndbox>
	</object>
</annotation>
